my_datetime_library/__init__.py
my_datetime_library/calendar_utils.py
my_datetime_library/constants.py
my_datetime_library/duration.py
my_datetime_library/leap_seconds.py
my_datetime_library/test_core_units.py
my_datetime_library/test_timezone.py
my_datetime_library/timepoint.py
my_datetime_library/timezone.py
my_datetime_library-0.1.0.dist-info/METADATA
my_datetime_library-0.1.0.dist-info/WHEEL
my_datetime_library-0.1.0.dist-info/top_level.txt
my_datetime_library-0.1.0.dist-info/RECORD
